sportspy/__init__.py
sportspy/anthropometry.py
sportspy/load.py
sportspy/somato.png
sportspy-0.0.4.dist-info/License.txt
sportspy-0.0.4.dist-info/METADATA
sportspy-0.0.4.dist-info/WHEEL
sportspy-0.0.4.dist-info/top_level.txt
sportspy-0.0.4.dist-info/RECORD
