Metadata-Version: 2.1
Name: sportspy
Version: 0.0.4
Summary: Sportspy package will be going to help sports statisticians , sports analyst and sports scientist to analyze team or individuals performance and fitness.
Home-page: https://github.com/pathakswetank/sportspy
Author: Swetank Pathak
Author-email: swetankpathak@gmail.com
License: UNKNOWN
Project-URL: Bug Tracker, https://github.com/pathakswetank/sportspy/issues
Platform: UNKNOWN
Classifier: Programming Language :: Python :: 3
Classifier: License :: OSI Approved :: MIT License
Classifier: Operating System :: OS Independent
Requires-Python: >=3.6
License-File: License.txt
